{
	"version": 2,
	"data": {
		"api::job.job": {
			"1": {
				"id": 1,
				"name": "Guerrero",
				"skill": "Puede mover o romper obstáculos.",
				"createdAt": "2022-12-10T12:00:01.839Z",
				"updatedAt": "2022-12-16T12:18:01.104Z",
				"publishedAt": "2022-12-10T12:00:14.130Z",
				"bonusStat": 1,
				"bonusType": "strength",
				"createdBy": null,
				"updatedBy": null
			},
			"2": {
				"id": 2,
				"name": "Mago",
				"skill": "Usa hechizos de magía elemental, defensivos, ofensivos y de invocación.",
				"createdAt": "2022-12-10T12:01:35.833Z",
				"updatedAt": "2022-12-16T12:17:54.970Z",
				"publishedAt": "2022-12-10T12:01:37.479Z",
				"bonusStat": 1,
				"bonusType": "intelligence",
				"createdBy": null,
				"updatedBy": null
			},
			"3": {
				"id": 3,
				"name": "Pícaro",
				"skill": "Puede pasar desapercibido, puede escalar y puede abrir cerraduras.",
				"createdAt": "2022-12-10T12:02:21.234Z",
				"updatedAt": "2022-12-16T12:17:47.351Z",
				"publishedAt": "2022-12-10T12:02:22.926Z",
				"bonusStat": 1,
				"bonusType": "agility",
				"createdBy": null,
				"updatedBy": null
			},
			"4": {
				"id": 4,
				"name": "Clérigo",
				"skill": "Usa hechizos de curación, potenciadores, defensivos y ofensivos.",
				"createdAt": "2022-12-10T12:02:56.962Z",
				"updatedAt": "2022-12-16T12:18:30.965Z",
				"publishedAt": "2022-12-10T12:02:58.379Z",
				"bonusStat": 1,
				"bonusType": "endurance",
				"createdBy": null,
				"updatedBy": null
			},
			"5": {
				"id": 5,
				"name": "Druida",
				"skill": "Se pueden transformar en su espíritu animal. Pueden hablar con animales.",
				"createdAt": "2022-12-10T12:04:26.456Z",
				"updatedAt": "2022-12-16T12:18:08.220Z",
				"publishedAt": "2022-12-10T12:04:27.700Z",
				"bonusStat": 1,
				"bonusType": "perception",
				"createdBy": null,
				"updatedBy": null
			}
		}
	}
}